seclab_taskflow_agent/__about__.py
seclab_taskflow_agent/__init__.py
seclab_taskflow_agent/__main__.py
seclab_taskflow_agent/agent.py
seclab_taskflow_agent/available_tools.py
seclab_taskflow_agent/banner.py
seclab_taskflow_agent/capi.py
seclab_taskflow_agent/env_utils.py
seclab_taskflow_agent/mcp_utils.py
seclab_taskflow_agent/path_utils.py
seclab_taskflow_agent/render_utils.py
seclab_taskflow_agent/shell_utils.py
seclab_taskflow_agent/mcp_servers/codeql/client.py
seclab_taskflow_agent/mcp_servers/codeql/mcp_server.py
seclab_taskflow_agent/mcp_servers/codeql/jsonrpyc/LICENSE
seclab_taskflow_agent/mcp_servers/codeql/jsonrpyc/__init__.py
seclab_taskflow_agent/mcp_servers/codeql/jsonrpyc/__meta__.py
seclab_taskflow_agent/mcp_servers/codeql/jsonrpyc/py.typed
seclab_taskflow_agent/mcp_servers/codeql/queries/README.md
seclab_taskflow_agent/mcp_servers/codeql/queries/mcp-cpp/absolute_to_relative.ql
seclab_taskflow_agent/mcp_servers/codeql/queries/mcp-cpp/call_graph_from.ql
seclab_taskflow_agent/mcp_servers/codeql/queries/mcp-cpp/call_graph_from_to.ql
seclab_taskflow_agent/mcp_servers/codeql/queries/mcp-cpp/call_graph_to.ql
seclab_taskflow_agent/mcp_servers/codeql/queries/mcp-cpp/codeql-pack.lock.yml
seclab_taskflow_agent/mcp_servers/codeql/queries/mcp-cpp/declaration_location_for_variable.ql
seclab_taskflow_agent/mcp_servers/codeql/queries/mcp-cpp/definition_location_for_function.ql
seclab_taskflow_agent/mcp_servers/codeql/queries/mcp-cpp/list_functions.ql
seclab_taskflow_agent/mcp_servers/codeql/queries/mcp-cpp/locations.qll
seclab_taskflow_agent/mcp_servers/codeql/queries/mcp-cpp/qlpack.yml
seclab_taskflow_agent/mcp_servers/codeql/queries/mcp-cpp/relative_to_absolute.ql
seclab_taskflow_agent/mcp_servers/codeql/queries/mcp-cpp/stmt_location.ql
seclab_taskflow_agent/mcp_servers/codeql/queries/mcp-js/absolute_to_relative.ql
seclab_taskflow_agent/mcp_servers/codeql/queries/mcp-js/call_graph_from.ql
seclab_taskflow_agent/mcp_servers/codeql/queries/mcp-js/call_graph_to.ql
seclab_taskflow_agent-0.0.10.dist-info/METADATA
seclab_taskflow_agent-0.0.10.dist-info/WHEEL
seclab_taskflow_agent-0.0.10.dist-info/licenses/LICENSE
seclab_taskflow_agent-0.0.10.dist-info/licenses/NOTICE
seclab_taskflow_agent-0.0.10.dist-info/RECORD
