Metadata-Version: 2.4
Name: seclab-taskflow-agent
Version: 0.0.10
Summary: A taskflow agent for the SecLab project, enabling secure and automated workflow execution.
Project-URL: Source, https://github.com/GitHubSecurityLab/seclab-taskflow-agent
Project-URL: Issues, https://github.com/GitHubSecurityLab/seclab-taskflow-agent/issues
Author-email: GitHub Security Lab <securitylab@github.com>
License-Expression: MIT
License-File: LICENSE
License-File: NOTICE
Classifier: Development Status :: 4 - Beta
Classifier: Programming Language :: Python
Classifier: Programming Language :: Python :: 3.10
Classifier: Programming Language :: Python :: 3.11
Classifier: Programming Language :: Python :: 3.12
Classifier: Programming Language :: Python :: Implementation :: CPython
Classifier: Programming Language :: Python :: Implementation :: PyPy
Requires-Python: >=3.10
Requires-Dist: aiofiles==24.1.0
Requires-Dist: annotated-types==0.7.0
Requires-Dist: anyio==4.9.0
Requires-Dist: attrs==25.3.0
Requires-Dist: authlib==1.6.6
Requires-Dist: certifi==2025.6.15
Requires-Dist: cffi==2.0.0
Requires-Dist: charset-normalizer==3.4.2
Requires-Dist: click==8.2.1
Requires-Dist: colorama==0.4.6
Requires-Dist: cryptography==45.0.7
Requires-Dist: cyclopts==3.24.0
Requires-Dist: distro==1.9.0
Requires-Dist: dnspython==2.8.0
Requires-Dist: docstring-parser==0.17.0
Requires-Dist: docutils==0.22
Requires-Dist: email-validator==2.3.0
Requires-Dist: exceptiongroup==1.3.0
Requires-Dist: fastmcp==2.12.2
Requires-Dist: griffe==1.7.3
Requires-Dist: h11==0.16.0
Requires-Dist: httpcore==1.0.9
Requires-Dist: httpx-sse==0.4.1
Requires-Dist: httpx==0.28.1
Requires-Dist: idna==3.10
Requires-Dist: importlib-metadata==8.7.0
Requires-Dist: isodate==0.7.2
Requires-Dist: jedi==0.19.2
Requires-Dist: jiter==0.10.0
Requires-Dist: jsonschema-path==0.3.4
Requires-Dist: jsonschema-specifications==2025.4.1
Requires-Dist: jsonschema==4.24.0
Requires-Dist: lazy-object-proxy==1.12.0
Requires-Dist: markdown-it-py==3.0.0
Requires-Dist: markupsafe==3.0.2
Requires-Dist: mcp==1.13.1
Requires-Dist: mdurl==0.1.2
Requires-Dist: more-itertools==10.8.0
Requires-Dist: openai-agents==0.2.11
Requires-Dist: openai==1.107.0
Requires-Dist: openapi-core==0.19.5
Requires-Dist: openapi-pydantic==0.5.1
Requires-Dist: openapi-schema-validator==0.6.3
Requires-Dist: openapi-spec-validator==0.7.2
Requires-Dist: parse==1.20.2
Requires-Dist: parso==0.8.4
Requires-Dist: pathable==0.4.4
Requires-Dist: platformdirs==4.5.0
Requires-Dist: pluggy==1.6.0
Requires-Dist: pycparser==2.23
Requires-Dist: pydantic-core==2.33.2
Requires-Dist: pydantic-settings==2.10.1
Requires-Dist: pydantic==2.11.7
Requires-Dist: pygments==2.19.2
Requires-Dist: pyperclip==1.9.0
Requires-Dist: python-dotenv==1.1.1
Requires-Dist: python-lsp-jsonrpc==1.1.2
Requires-Dist: python-lsp-server==1.12.2
Requires-Dist: python-multipart==0.0.22
Requires-Dist: pyyaml==6.0.2
Requires-Dist: referencing==0.36.2
Requires-Dist: requests==2.32.4
Requires-Dist: rfc3339-validator==0.1.4
Requires-Dist: rich-rst==1.3.1
Requires-Dist: rich==14.0.0
Requires-Dist: rpds-py==0.26.0
Requires-Dist: shellingham==1.5.4
Requires-Dist: six==1.17.0
Requires-Dist: sniffio==1.3.1
Requires-Dist: sqlalchemy==2.0.41
Requires-Dist: sse-starlette==2.4.1
Requires-Dist: starlette==0.49.1
Requires-Dist: strenum==0.4.15
Requires-Dist: tqdm==4.67.1
Requires-Dist: typer==0.16.0
Requires-Dist: types-requests==2.32.4.20250611
Requires-Dist: typing-extensions==4.14.1
Requires-Dist: typing-inspection==0.4.1
Requires-Dist: ujson==5.10.0
Requires-Dist: urllib3==2.6.3
Requires-Dist: uvicorn==0.35.0
Requires-Dist: zipp==3.23.0
